naverlogin.py
naverlogin-1.0.2.dist-info/LICENSE
naverlogin-1.0.2.dist-info/METADATA
naverlogin-1.0.2.dist-info/WHEEL
naverlogin-1.0.2.dist-info/top_level.txt
naverlogin-1.0.2.dist-info/RECORD
